reify.py
reify-0.4.dist-info/LICENSE
reify-0.4.dist-info/METADATA
reify-0.4.dist-info/WHEEL
reify-0.4.dist-info/entry_points.txt
reify-0.4.dist-info/top_level.txt
reify-0.4.dist-info/RECORD
